cloudmesh_cloud-4.4.1-nspkg.pth
cloudmesh/cloud/__init__.py
cloudmesh/cloud/__version__.py
cloudmesh/compute/__init__.py
cloudmesh/compute/docker/Provider.py
cloudmesh/compute/docker/__init__.py
cloudmesh/compute/libcloud/Provider.py
cloudmesh/compute/libcloud/__init__.py
cloudmesh/compute/virtualbox/Provider.py
cloudmesh/compute/virtualbox/__init__.py
cloudmesh/compute/vm/Provider.py
cloudmesh/compute/vm/__init__.py
cloudmesh/container/__init__.py
cloudmesh/container/command/__init__.py
cloudmesh/container/command/container.py
cloudmesh/data/__init__.py
cloudmesh/data/api/CloudFile.py
cloudmesh/data/api/Driver.py
cloudmesh/data/api/File.py
cloudmesh/data/api/__init__.py
cloudmesh/data/api/data.py
cloudmesh/data/api/db/DBProviderABC.py
cloudmesh/data/api/db/LocalDBProvider.py
cloudmesh/data/api/db/__init__.py
cloudmesh/data/api/storage/AzureStorageProvider.py
cloudmesh/data/api/storage/LocalStorageProvider.py
cloudmesh/data/api/storage/StorageProviderABC.py
cloudmesh/data/api/storage/__init__.py
cloudmesh/data/command/__init__.py
cloudmesh/data/command/data.py
cloudmesh/etc/__init__.py
cloudmesh/flavor/__init__.py
cloudmesh/flavor/command/__init__.py
cloudmesh/flavor/command/flavor.py
cloudmesh/group/Group.py
cloudmesh/group/__init__.py
cloudmesh/group/command/__init__.py
cloudmesh/group/command/group.py
cloudmesh/image/Image.py
cloudmesh/image/__init__.py
cloudmesh/image/command/__init__.py
cloudmesh/image/command/image.py
cloudmesh/init/__init__.py
cloudmesh/init/command/__init__.py
cloudmesh/init/command/init.py
cloudmesh/ip/__init__.py
cloudmesh/ip/command/__init__.py
cloudmesh/ip/command/ip.py
cloudmesh/key/Key.py
cloudmesh/key/__init__.py
cloudmesh/key/command/__init__.py
cloudmesh/key/command/key.py
cloudmesh/open/__init__.py
cloudmesh/open/command/__init__.py
cloudmesh/open/command/open.py
cloudmesh/register/AWSRegister.py
cloudmesh/register/AzRegister.py
cloudmesh/register/Entry.py
cloudmesh/register/Register.py
cloudmesh/register/__init__.py
cloudmesh_cloud-4.4.1.dist-info/LICENSE
cloudmesh_cloud-4.4.1.dist-info/METADATA
cloudmesh_cloud-4.4.1.dist-info/WHEEL
cloudmesh_cloud-4.4.1.dist-info/namespace_packages.txt
cloudmesh_cloud-4.4.1.dist-info/top_level.txt
cloudmesh_cloud-4.4.1.dist-info/RECORD
