Metadata-Version: 2.1
Name: cloudmesh-cloud
Version: 4.4.1
Summary: Cloudmesh Multicloud Cloud Plugins for Cloudmesh cmd5 CMD
Home-page: https://github.com/cloudmesh/cloudmesh-cloud
Author: Gregor von Laszewski
Author-email: laszewski@gmail.com
License: Apache 2.0
Platform: UNKNOWN
Classifier: Development Status :: 5 - Production/Stable
Classifier: Environment :: Console
Classifier: Environment :: MacOS X
Classifier: Environment :: OpenStack
Classifier: Environment :: Other Environment
Classifier: Environment :: Plugins
Classifier: Intended Audience :: Information Technology
Classifier: Intended Audience :: Developers
Classifier: Intended Audience :: Education
Classifier: Intended Audience :: Science/Research
Classifier: Intended Audience :: System Administrators
Classifier: License :: OSI Approved :: Apache Software License
Classifier: Natural Language :: English
Classifier: Operating System :: OS Independent
Classifier: Operating System :: MacOS
Classifier: Operating System :: Microsoft :: Windows :: Windows 10
Classifier: Operating System :: Unix
Classifier: Programming Language :: Python
Classifier: Programming Language :: Python :: 3
Classifier: Programming Language :: Python :: 3.7
Classifier: Programming Language :: Python :: 3.8
Classifier: Topic :: Internet
Classifier: Topic :: Scientific/Engineering
Classifier: Topic :: Software Development :: Libraries
Classifier: Topic :: Software Development :: User Interfaces
Classifier: Topic :: System
Classifier: Topic :: System :: Distributed Computing
Classifier: Topic :: System :: Shells
Classifier: Topic :: Utilities
Requires-Dist: Flask-PyMongo
Requires-Dist: PyYAML
Requires-Dist: apache-libcloud
Requires-Dist: beautifulsoup4
Requires-Dist: cloudmesh-abstract
Requires-Dist: cloudmesh-admin
Requires-Dist: cloudmesh-cmd5
Requires-Dist: cloudmesh-configuration
Requires-Dist: cloudmesh-inventory
Requires-Dist: cloudmesh-sys
Requires-Dist: dateparser
Requires-Dist: docker
Requires-Dist: docopt
Requires-Dist: flask
Requires-Dist: humanize
Requires-Dist: idna
Requires-Dist: munch
Requires-Dist: oyaml
Requires-Dist: progress
Requires-Dist: psutil
Requires-Dist: pymongo
Requires-Dist: recommonmark
Requires-Dist: requests
Requires-Dist: selenium
Requires-Dist: tabulate
